setup.py
telstra_sms_sdk/__init__.py
telstra_sms_sdk/sms.py
telstra_sms_sdk.egg-info/PKG-INFO
telstra_sms_sdk.egg-info/SOURCES.txt
telstra_sms_sdk.egg-info/dependency_links.txt
telstra_sms_sdk.egg-info/requires.txt
telstra_sms_sdk.egg-info/top_level.txt