Metadata-Version: 1.0
Name: telstra-sms-sdk
Version: 0.0.7
Summary: A 3rd party python sdk allow you to send sms easily.
Home-page: https://github.com/arkilis/telstra-sms-sdk
Author: Yang Liu
Author-email: arkilis@gmail.com
License: MIT License
Keywords: telstra,sms,sdk
Platform: any
